{
  "study": {
    "version": "14.0",
    "student": "Sailor",
    "syncedAt": "2026-07-22T06:23:53.580Z",
    "xp": 32717,
    "rank": {
      "cn": "海军上将",
      "en": "Admiral",
      "min": 32000,
      "color": "#d4a01a"
    },
    "coverage": {
      "done": 11,
      "total": 17
    },
    "units": [
      {
        "id": "ZH25",
        "subj": "cn",
        "title": "成语精细辨析 IV",
        "en": "Idioms IV",
        "icon": "🎓",
        "best": "15/15",
        "ratio": 1,
        "status": "mastered",
        "total": 15
      },
      {
        "id": "ZH26",
        "subj": "cn",
        "title": "递进与转折专项 + 识字 Day 25",
        "en": "Progression vs Contrast",
        "icon": "⚖️",
        "best": "15/15",
        "ratio": 1,
        "status": "mastered",
        "total": 15
      },
      {
        "id": "ZH27",
        "subj": "cn",
        "title": "长文阅读·蚂蚁的城市",
        "en": "Reading: Ant City",
        "icon": "🐜",
        "best": "15/15",
        "ratio": 1,
        "status": "mastered",
        "total": 15
      },
      {
        "id": "ZH28",
        "subj": "cn",
        "title": "病句门诊 III + 识字 Day 26",
        "en": "Sentence Clinic III",
        "icon": "🩺",
        "best": "15/15",
        "ratio": 1,
        "status": "mastered",
        "total": 15
      },
      {
        "id": "MA25",
        "subj": "math",
        "title": "Exponents & Order of Ops III",
        "en": "乘方专项·混合运算",
        "icon": "🚀",
        "best": "15/15",
        "ratio": 1,
        "status": "mastered",
        "total": 15
      },
      {
        "id": "MA26",
        "subj": "math",
        "title": "Integers & the Number Line",
        "en": "负数初步（G6 新内容）",
        "icon": "🌡️",
        "best": "15/15",
        "ratio": 1,
        "status": "mastered",
        "total": 15
      },
      {
        "id": "MA27",
        "subj": "math",
        "title": "Ratios, Rates & Working Backwards",
        "en": "比与比率·逆向求整体",
        "icon": "🧮",
        "best": "15/15",
        "ratio": 1,
        "status": "mastered",
        "total": 15
      },
      {
        "id": "MA28",
        "subj": "math",
        "title": "Geometry IV & Multi-step Problems",
        "en": "复合图形·三步应用题",
        "icon": "🏗️",
        "best": "15/15",
        "ratio": 1,
        "status": "mastered",
        "total": 15
      },
      {
        "id": "SC13",
        "subj": "sci",
        "title": "Ecosystems & Food Chains",
        "en": "生态系统与食物链",
        "icon": "🦊",
        "best": "16/16",
        "ratio": 1,
        "status": "mastered",
        "total": 16
      },
      {
        "id": "SC14",
        "subj": "sci",
        "title": "Light & Sound",
        "en": "光与声",
        "icon": "🔦",
        "best": null,
        "ratio": null,
        "status": "todo",
        "total": 16
      },
      {
        "id": "SC15",
        "subj": "sci",
        "title": "Electricity & Circuits",
        "en": "电与电路",
        "icon": "🔋",
        "best": null,
        "ratio": null,
        "status": "todo",
        "total": 16
      },
      {
        "id": "EN24",
        "subj": "en",
        "title": "Reading Poetry: The Harbour at Night",
        "en": "诗歌阅读（新体裁）",
        "icon": "🌙",
        "best": "16/16",
        "ratio": 1,
        "status": "mastered",
        "total": 16
      },
      {
        "id": "EN25",
        "subj": "en",
        "title": "Reading: Icebergs",
        "en": "说明文阅读·冰山",
        "icon": "🧊",
        "best": null,
        "ratio": null,
        "status": "todo",
        "total": 16
      },
      {
        "id": "EN26",
        "subj": "en",
        "title": "Grammar & Conventions V",
        "en": "撇号·引号·段落改错",
        "icon": "🖊️",
        "best": null,
        "ratio": null,
        "status": "todo",
        "total": 15
      },
      {
        "id": "EN27",
        "subj": "en",
        "title": "Writing Studio VI: Paragraphs",
        "en": "汉堡段落写作",
        "icon": "🍔",
        "best": null,
        "ratio": null,
        "status": "todo",
        "total": 5
      },
      {
        "id": "FR13",
        "subj": "fr",
        "title": "Verbes en -er · La négation",
        "en": "-er 动词变位·否定句",
        "icon": "🗣️",
        "best": "15/15",
        "ratio": 1,
        "status": "mastered",
        "total": 15
      },
      {
        "id": "FR14",
        "subj": "fr",
        "title": "Les nombres · Lecture IV",
        "en": "数字11-20·阅读：Théo 的野餐",
        "icon": "🥪",
        "best": null,
        "ratio": null,
        "status": "todo",
        "total": 15
      }
    ],
    "mistakesByUnit": {
      "Exponents & Order of Ops III": [
        {
          "q": "3² + 4² = ?",
          "x": "17",
          "r": "25",
          "tier": 3
        },
        {
          "q": "2 × 3² = ?",
          "x": "12",
          "r": "18",
          "tier": 3
        },
        {
          "q": "20 − 2³ = ?",
          "x": "2",
          "r": "12",
          "tier": 3
        },
        {
          "q": "(2 + 3)² = ?",
          "x": "36",
          "r": "25",
          "tier": 3
        },
        {
          "q": "4³ = ?",
          "x": "2",
          "r": "64",
          "tier": 3
        },
        {
          "q": "18 − 12 ÷ 3 + 2² = ?",
          "x": "6",
          "r": "18",
          "tier": 3
        },
        {
          "q": "Which expression matches: 'the square of the sum of 4 and 1'?",
          "x": "4 + 1²",
          "r": "(4 + 1)²",
          "tier": 3
        },
        {
          "q": "Which equations are TRUE? (select all)",
          "x": "(1 + 2)² = 9、2³ = 6",
          "r": "3² = 9、10 − 2² = 6、(1 + 2)² = 9",
          "tier": 3
        },
        {
          "q": "Which expressions equal 16? (select all)",
          "x": "4 × 4、8 + 8、2⁴",
          "r": "4²、2⁴、8 + 8、4 × 4",
          "tier": 3
        }
      ],
      "Integers & the Number Line": [
        {
          "q": "4 − 9 = ?",
          "x": "6",
          "r": "-5",
          "tier": 3
        },
        {
          "q": "−2 − 3 = ?",
          "x": "1",
          "r": "-5",
          "tier": 3
        },
        {
          "q": "0 − 7 = ?",
          "x": "8",
          "r": "-7",
          "tier": 2
        },
        {
          "q": "The temperature is −8°C. It rises 5°C. What is it now? (number only)",
          "x": "6",
          "r": "-3",
          "tier": 3
        },
        {
          "q": "A diver is at −12 m and goes DOWN 6 m more. Where is she? (number only)",
          "x": "3",
          "r": "-18",
          "tier": 3
        },
        {
          "q": "Order from LEAST to GREATEST: 2, −5, 0, −1",
          "x": "−1, −5, 0, 2",
          "r": "−5, −1, 0, 2",
          "tier": 3
        },
        {
          "q": "The opposite of −3 is —",
          "x": "0",
          "r": "3",
          "tier": 2
        },
        {
          "q": "Basement floor B2 in an elevator is best written as —",
          "x": "0.2",
          "r": "−2",
          "tier": 1
        },
        {
          "q": "Which numbers are LESS than 0? (select all)",
          "x": "−1",
          "r": "−1、−15、−0.5",
          "tier": 3
        },
        {
          "q": "Which comparisons are TRUE? (select all)",
          "x": "−5 < −2、−3 > 1",
          "r": "−5 < −2、0 > −9、−10 < −1",
          "tier": 3
        },
        {
          "q": "Which situations describe a NEGATIVE number? (select all)",
          "x": "you earn 10 dollars、parking level B3、the temperature falls to 5 degrees below zero",
          "r": "6 m below sea level、the temperature falls to 5 degrees below zero、parking level B3",
          "tier": 3
        }
      ],
      "长文阅读·蚂蚁的城市": [
        {
          "q": "蚁后在王国里负责——",
          "x": "挖通道",
          "r": "产卵",
          "tier": 1
        },
        {
          "q": "最忙的是哪种蚂蚁？它们不做下面哪件事？",
          "x": "兵蚁；产卵",
          "r": "工蚁；守在入口",
          "tier": 3
        },
        {
          "q": "文中说兵蚁「像门口的卫兵」，这是——",
          "x": "下定义",
          "r": "打比方",
          "tier": 2
        },
        {
          "q": "同伴能准确找到食物，是因为——",
          "x": "听到了声音",
          "r": "顺着前面蚂蚁留下的气味走",
          "tier": 2
        },
        {
          "q": "用手指在蚂蚁队伍中间划一下，蚂蚁会乱成一团，原因是——",
          "x": "它们害怕手指",
          "r": "气味路被擦掉了，它们失去了方向",
          "tier": 3
        },
        {
          "q": "「一个大蚁巢常常住着几万只蚂蚁」用的说明方法是——",
          "x": "提问题",
          "r": "列数字",
          "tier": 2
        },
        {
          "q": "下面哪些说法与文章相符？（多选）",
          "x": "蚂蚁靠气味和触角传递消息",
          "r": "蚁巢通道最深能到两米多、蚂蚁靠气味和触角传递消息、擦掉气味后蚂蚁会迷路",
          "tier": 3
        },
        {
          "q": "文中哪些地方用了「打比方」？（多选）",
          "x": "通道能挖到两米多深",
          "r": "蚁巢像一栋倒着建的高楼、蚁后是王国的「心脏」、兵蚁像门口的卫兵",
          "tier": 3
        },
        {
          "q": "如果给文章换个题目，下面哪些合适？（多选）",
          "x": "《高楼是怎样建成的》",
          "r": "《地下的蚂蚁王国》、《分工合作的小蚂蚁》、《神奇的「气味路」和蚂蚁的家》",
          "tier": 3
        }
      ],
      "成语精细辨析 IV": [
        {
          "q": "「为了造出这艘船模，他常常________，连饭都忘了吃。」填——",
          "x": "井井有条",
          "r": "废寝忘食",
          "tier": 2
        },
        {
          "q": "「练字要________，三天打鱼两天晒网是练不好的。」填——",
          "x": "恍然大悟",
          "r": "持之以恒",
          "tier": 3
        },
        {
          "q": "「他________地盯着显微镜，生怕错过任何变化。」填最贴切的成语。",
          "x": "日积月累",
          "r": "目不转睛",
          "tier": 3
        },
        {
          "q": "「妹妹________地拼模型，谁叫她都听不见。」填——",
          "x": "川流不息",
          "r": "专心致志",
          "tier": 3
        },
        {
          "q": "下面哪句成语用错了？",
          "x": "经过日积月累，他认识了很多字。",
          "r": "他持之以恒地打了一个哈欠。",
          "tier": 3
        },
        {
          "q": "哪些句子的成语使用正确？（多选）",
          "x": "他废寝忘食地准备比赛。",
          "r": "他废寝忘食地准备比赛。、展览馆里参观的人络绎不绝。、坚持锻炼要持之以恒。",
          "tier": 3
        },
        {
          "q": "哪些搭配是正确的？（多选）",
          "x": "异口同声地点头",
          "r": "字写得一丝不苟、知识靠日积月累、做事持之以恒",
          "tier": 3
        },
        {
          "q": "「都等不及了」——「迫不________待」。点选正确的字。",
          "x": "急",
          "r": "及",
          "tier": 3
        },
        {
          "q": "「知识要一点一点________累。」点选正确的字。",
          "x": "织",
          "r": "积",
          "tier": 2
        },
        {
          "q": "「他读书读得废寝________食。」点选正确的字。",
          "x": "盲",
          "r": "忘",
          "tier": 2
        },
        {
          "q": "「专心________志，才能把事做好。」点选正确的字。",
          "x": "至",
          "r": "致",
          "tier": 3
        }
      ],
      "Ecosystems & Food Chains": [
        {
          "q": "Which chain is in the CORRECT order?",
          "x": "bird → hawk → grass → grasshopper",
          "r": "grass → grasshopper → bird → hawk",
          "tier": 3
        },
        {
          "q": "Which of these are PRODUCERS? (select all)",
          "x": "grass",
          "r": "seaweed、grass、an oak tree",
          "tier": 3
        },
        {
          "q": "If the small fish in a lake all died, which effects are LIKELY? (select all)",
          "x": "birds that eat small fish would leave or go hungry",
          "r": "big fish would have less to eat、birds that eat small fish would leave or go hungry、the tiny water plants they ate might grow more",
          "tier": 3
        },
        {
          "q": "Which statements about ecosystems are TRUE? (select all)",
          "x": "Arrows in a chain point at the food.",
          "r": "Energy enters most ecosystems as sunlight.、Decomposers return nutrients to the soil.、A food web is many chains connected.",
          "tier": 3
        }
      ],
      "Reading Poetry: The Harbour at Night": [
        {
          "q": "How many STANZAS does this poem have?",
          "x": "two",
          "r": "three",
          "tier": 1
        },
        {
          "q": "How many LINES are in each stanza?",
          "x": "twelve",
          "r": "four",
          "tier": 1
        },
        {
          "q": "Which word rhymes with 'rest' in stanza 1?",
          "x": "boats",
          "r": "nest",
          "tier": 1
        },
        {
          "q": "The rhyme pattern of each stanza is —",
          "x": "ABAB (alternating)",
          "r": "AABB (pairs)",
          "tier": 3
        },
        {
          "q": "'Like tired birds that seek their nest' is a —",
          "x": "personification",
          "r": "simile",
          "tier": 2
        },
        {
          "q": "The MOOD of this poem is —",
          "x": "scary and stormy",
          "r": "calm and peaceful",
          "tier": 3
        },
        {
          "q": "'Morning light unties the ribbons of the night' most likely means —",
          "x": "someone forgot their ribbons",
          "r": "dawn slowly ends the darkness",
          "tier": 3
        },
        {
          "q": "Which lines contain SIMILES? (select all)",
          "x": "The lighthouse is a patient eye、Like soft knocks on a wooden door",
          "r": "Like tired birds that seek their nest、Like soft knocks on a wooden door",
          "tier": 3
        },
        {
          "q": "Which poetic tools appear in this poem? (select all)",
          "x": "metaphor、simile、personification",
          "r": "simile、metaphor、personification、rhyme",
          "tier": 3
        },
        {
          "q": "Which statements about the poem are TRUE? (select all)",
          "x": "The poem ends at sunrise — morning light appears.、The lighthouse beam moves left and right.、The poem describes a violent storm.、The boats are compared to tired birds.",
          "r": "The poem is set at night.、The boats are compared to tired birds.、The lighthouse beam moves left and right.、The poem ends at sunrise — morning light appears.",
          "tier": 3
        },
        {
          "q": "Which pairs of words RHYME in this poem? (select all)",
          "x": "light / night",
          "r": "tune / moon、shore / door、light / night、eye / by",
          "tier": 3
        }
      ],
      "Verbes en -er · La négation": [
        {
          "q": "Complete: 'Je ____ français.' (to speak)",
          "x": "parles",
          "r": "parle",
          "tier": 2
        },
        {
          "q": "Complete: 'Elle ____ à Toronto.' (to live)",
          "x": "habitons",
          "r": "habite",
          "tier": 2
        },
        {
          "q": "'Je ne parle pas anglais.' means —",
          "x": "You do not speak English.",
          "r": "I do not speak English.",
          "tier": 2
        },
        {
          "q": "Which is the correct NEGATIVE of 'Il joue.'?",
          "x": "Ne il joue pas.",
          "r": "Il ne joue pas.",
          "tier": 3
        },
        {
          "q": "Which is correct before a vowel?",
          "x": "Je ne aime pas les épinards.",
          "r": "Je n'aime pas les épinards.",
          "tier": 3
        },
        {
          "q": "'Nous ne mangeons pas de poisson.' means —",
          "x": "They do not eat fish.",
          "r": "We do not eat fish.",
          "tier": 3
        },
        {
          "q": "How do you say 'She does not play'?",
          "x": "Nous ne jouons pas.",
          "r": "Elle ne joue pas.",
          "tier": 3
        },
        {
          "q": "Complete: 'Est-ce que nous ____ ensemble ?' (to play)",
          "x": "joue",
          "r": "jouons",
          "tier": 3
        },
        {
          "q": "Which sentences are CORRECT? (select all)",
          "x": "Elle habitons à Paris.、Je parles très vite.、Nous aimons la mer.",
          "r": "Je parle français.、Tu joues au parc.、Nous aimons la mer.",
          "tier": 3
        },
        {
          "q": "Which are CORRECT negative sentences? (select all)",
          "x": "Il n'aime pas le café.",
          "r": "Je ne joue pas.、Il n'aime pas le café.、Nous ne parlons pas fort.",
          "tier": 3
        }
      ],
      "递进与转折专项 + 识字 Day 25": [
        {
          "q": "「这条船________跑得快，________特别省油。」填——",
          "x": "尽管…还是…",
          "r": "不但…而且…",
          "tier": 2
        },
        {
          "q": "「________下着大雨，运动会________照常举行。」填——",
          "x": "不是…就是…",
          "r": "尽管…还是…",
          "tier": 2
        },
        {
          "q": "「妹妹________会背这首诗，________能讲出诗的意思。」填——",
          "x": "虽然…但是…",
          "r": "不仅…还…",
          "tier": 3
        },
        {
          "q": "「他________个子不高，________跳得比谁都远。」填——",
          "x": "一…就…",
          "r": "虽然…但是…",
          "tier": 2
        },
        {
          "q": "「爷爷不但会修船，而且会造船。」这句话的关系是——",
          "x": "转折",
          "r": "递进",
          "tier": 2
        },
        {
          "q": "哪些关联词表示「递进」？（多选）",
          "x": "虽然…但是…、不但…而且…、不仅…还…",
          "r": "不但…而且…、不仅…还…、甚至",
          "tier": 3
        },
        {
          "q": "哪些句子用了「转折」关系？（多选）",
          "x": "虽然他很累，但是他坚持跑完了。、一到周末，我们就去图书馆。、他不但会唱歌，而且会跳舞。",
          "r": "虽然他很累，但是他坚持跑完了。、天气尽管很冷，大家还是来了。、这本书很旧，却很有意思。",
          "tier": 3
        },
        {
          "q": "哪些句子的关联词使用正确？（多选）",
          "x": "虽然下雨了，但是比赛照常进行。、妈妈虽然工作忙，但是每天陪我读书。、尽管他不会游泳，还是他喜欢大海。",
          "r": "他不但学习好，而且乐于助人。、虽然下雨了，但是比赛照常进行。、妈妈虽然工作忙，但是每天陪我读书。",
          "tier": 3
        },
        {
          "q": "「他每天很________就起床读书。」点选一个字。",
          "x": "晨",
          "r": "早",
          "tier": 2
        },
        {
          "q": "「中________十二点，太阳最高。」点选一个字。",
          "x": "许",
          "r": "午",
          "tier": 2
        },
        {
          "q": "「一小时有六十________钟。」点选一个字。",
          "x": "纷",
          "r": "分",
          "tier": 2
        }
      ],
      "病句门诊 III + 识字 Day 26": [
        {
          "q": "「通过这次比赛，使我明白了团结的力量。」怎样修改最恰当？",
          "x": "把「团结」改成「团洁」",
          "r": "删去「通过」或「使」",
          "tier": 3
        },
        {
          "q": "「他睡觉前总觉得口渴。」两个「觉」的读音是——",
          "x": "都读 jiào",
          "r": "jiào、jué",
          "tier": 3
        },
        {
          "q": "下面哪句话没有语病？",
          "x": "听了老师的话，受到了很大教育。",
          "r": "我们要发扬优点，改正缺点。",
          "tier": 3
        },
        {
          "q": "「他大概用了估计十分钟。」这句话的毛病是——",
          "x": "缺少主语",
          "r": "重复啰嗦",
          "tier": 2
        },
        {
          "q": "「哥哥________了我一支新铅笔。」点选一个字。",
          "x": "领",
          "r": "给",
          "tier": 2
        },
        {
          "q": "「我到处________不到我的橡皮了。」点选一个字。",
          "x": "托",
          "r": "找",
          "tier": 2
        },
        {
          "q": "「用完的东西要________回原来的地方。」点选一个字。",
          "x": "方",
          "r": "放",
          "tier": 2
        },
        {
          "q": "「请帮我把桌上的书________过来。」点选一个字。",
          "x": "合",
          "r": "拿",
          "tier": 3
        },
        {
          "q": "「作业写完要________好，别弄丢。」点选两个字。",
          "x": "放",
          "r": "放好",
          "tier": 3
        }
      ],
      "Ratios, Rates & Working Backwards": [
        {
          "q": "$12 for 3 notebooks. How much for ONE notebook? (number only)",
          "x": "1",
          "r": "4",
          "tier": 2
        },
        {
          "q": "A boat travels 45 km in 3 hours. How many km per hour?",
          "x": "3",
          "r": "15",
          "tier": 2
        },
        {
          "q": "2/3 of a number is 12. What is the number?",
          "x": "4",
          "r": "18",
          "tier": 3
        },
        {
          "q": "3/4 of a number is 21. What is the number?",
          "x": "6",
          "r": "28",
          "tier": 3
        },
        {
          "q": "25% of a number is 8. What is the number?",
          "x": "2",
          "r": "32",
          "tier": 3
        },
        {
          "q": "15% of 80 = ?",
          "x": "2",
          "r": "12",
          "tier": 3
        },
        {
          "q": "The ratio of boys to girls is 2:3. There are 8 boys. How many girls?",
          "x": "3",
          "r": "12",
          "tier": 3
        },
        {
          "q": "5/8 − 1/4 = ? (simplest form)",
          "x": "12",
          "r": "3/8",
          "tier": 3
        },
        {
          "q": "Simplify the ratio 12:18.",
          "x": "12:18 cannot simplify",
          "r": "2:3",
          "tier": 3
        },
        {
          "q": "Which ratio is EQUIVALENT to 3:5?",
          "x": "9:12",
          "r": "6:10",
          "tier": 2
        },
        {
          "q": "Which ratios are equivalent to 2:5? (select all)",
          "x": "5:2、8:20",
          "r": "4:10、6:15、8:20",
          "tier": 3
        },
        {
          "q": "Which are equal to 3/4? (select all)",
          "x": "0.75、9/12、6/8",
          "r": "75%、0.75、6/8、9/12",
          "tier": 3
        },
        {
          "q": "A recipe uses flour and sugar in the ratio 4:1. Which statements are TRUE? (select all)",
          "x": "12 cups flour needs 3 cups sugar",
          "r": "8 cups flour needs 2 cups sugar、flour is 4 times the sugar、12 cups flour needs 3 cups sugar",
          "tier": 3
        }
      ],
      "Geometry IV & Multi-step Problems": [
        {
          "q": "A parallelogram has base 8 and height 5. What is its AREA?",
          "x": "1",
          "r": "40",
          "tier": 2
        },
        {
          "q": "An L-shaped deck is a 10 by 6 rectangle with a 4 by 2 corner cut out. What is its AREA?",
          "x": "8",
          "r": "52",
          "tier": 3
        },
        {
          "q": "A triangle has base 12 and height 5. What is its AREA?",
          "x": "8",
          "r": "30",
          "tier": 3
        },
        {
          "q": "A box has volume 60. Its length is 5 and width is 3. What is its HEIGHT?",
          "x": "2",
          "r": "4",
          "tier": 3
        },
        {
          "q": "A box is 4 by 4 by 7. What is its VOLUME?",
          "x": "1",
          "r": "112",
          "tier": 3
        },
        {
          "q": "Solve: 2(x + 3) = 14. x = ?",
          "x": "7",
          "r": "4",
          "tier": 3
        },
        {
          "q": "Solve: 3(x − 2) = 15. x = ?",
          "x": "/",
          "r": "7",
          "tier": 3
        },
        {
          "q": "Kai buys 3 T-shirts at $12 each and pays with $50. How much CHANGE does he get?",
          "x": "7",
          "r": "14",
          "tier": 3
        },
        {
          "q": "To find the area of an L-shape, the BEST first move is —",
          "x": "multiply all the numbers you see",
          "r": "split it into rectangles",
          "tier": 2
        },
        {
          "q": "Which situation needs VOLUME?",
          "x": "how much rope goes around a field",
          "r": "how much water fills an aquarium",
          "tier": 2
        },
        {
          "q": "Which units measure AREA? (select all)",
          "x": "m²、cm²、cm³",
          "r": "cm²、m²、km²",
          "tier": 3
        },
        {
          "q": "Which statements are TRUE? (select all)",
          "x": "An L-shape's area can be found by subtracting the notch、Parallelogram area = base × height、Volume of a box = l × w × h",
          "r": "Triangle area = base × height ÷ 2、Parallelogram area = base × height、Volume of a box = l × w × h、An L-shape's area can be found by subtracting the notch",
          "tier": 3
        },
        {
          "q": "A captain buys 5 boxes of flags. Each box holds 8 flags. She gives away 12. Which steps find how many are LEFT? (select all)",
          "x": "multiply 5 × 8、start from 40、add 5 + 8",
          "r": "multiply 5 × 8、subtract 12 from the total、start from 40",
          "tier": 3
        }
      ],
      "Reading: Icebergs": [
        {
          "q": "When a huge chunk of ice breaks off a glacier, scientists call it —",
          "x": "melting",
          "r": "calving",
          "tier": 2
        }
      ]
    },
    "reviewQueue": [
      {
        "c": "及",
        "n": 1
      },
      {
        "c": "积",
        "n": 1
      },
      {
        "c": "忘",
        "n": 1
      },
      {
        "c": "致",
        "n": 1
      },
      {
        "c": "早",
        "n": 1
      },
      {
        "c": "午",
        "n": 1
      },
      {
        "c": "分",
        "n": 1
      },
      {
        "c": "给",
        "n": 1
      },
      {
        "c": "找",
        "n": 1
      },
      {
        "c": "放",
        "n": 1
      },
      {
        "c": "拿",
        "n": 1
      }
    ],
    "boxRemaining": 0,
    "writing": {},
    "packet": {
      "ver": "14.0",
      "date": "2026-07-11",
      "xp": 32717,
      "diag": {
        "chinese": {
          "score": 14,
          "total": 25,
          "pct": 56
        },
        "english": {
          "score": 7,
          "total": 8,
          "pct": 88
        },
        "math": {
          "score": 8,
          "total": 10,
          "pct": 80
        }
      },
      "lessonsDone": [
        "e1",
        "e5",
        "e3",
        "m7",
        "m1",
        "c5",
        "c6",
        "m8",
        "m3",
        "m4",
        "c1",
        "c2",
        "C1",
        "C2",
        "C3",
        "C4",
        "C5",
        "C6",
        "M1",
        "M2",
        "M3",
        "M4",
        "E1",
        "E2",
        "E3",
        "ZH1",
        "ZH2",
        "ZH3",
        "ZH4",
        "MA1",
        "MA2",
        "MA3",
        "MA4",
        "SC1",
        "SC2",
        "EN1",
        "EN2",
        "EN3",
        "FR1",
        "FR2",
        "ZH5",
        "ZH6",
        "ZH7",
        "ZH8",
        "MA5",
        "MA6",
        "MA7",
        "MA8",
        "SC3",
        "SC4",
        "EN4",
        "EN5",
        "EN6",
        "EN7",
        "FR3",
        "FR4",
        "SC6",
        "ZH9",
        "ZH10",
        "ZH11",
        "ZH12",
        "MA9",
        "MA10",
        "MA11",
        "MA12",
        "SC5",
        "EN8",
        "EN9",
        "EN11",
        "EN10",
        "FR6",
        "ZH13",
        "SC7",
        "ZH15",
        "MA16",
        "FR7",
        "FR8",
        "SC8",
        "EN12",
        "EN13",
        "EN14",
        "EN15",
        "ZH14",
        "ZH16",
        "MA13",
        "MA14",
        "MA15",
        "SC9",
        "EN16",
        "FR9",
        "ZH17",
        "ZH19",
        "ZH18",
        "MA20",
        "EN17",
        "EN19",
        "EN18",
        "MA18",
        "MA17",
        "MA19",
        "FR10",
        "ZH20",
        "SC10",
        "ZH23",
        "SC11",
        "SC12",
        "EN20",
        "FR11",
        "MA21",
        "MA22",
        "FR12",
        "ZH21",
        "ZH22",
        "ZH24",
        "EN23",
        "EN21",
        "EN22",
        "MA23",
        "MA24",
        "MA25",
        "MA26",
        "ZH27",
        "ZH25",
        "SC13",
        "EN24",
        "FR13",
        "ZH26",
        "ZH28",
        "MA27",
        "MA28"
      ],
      "unitBest": {
        "C1": "8/10",
        "C2": "10/10",
        "C3": "9/10",
        "C4": "8/10",
        "C5": "7/8",
        "C6": "10/10",
        "M1": "5/10",
        "M2": "9/10",
        "M3": "9/12",
        "M4": "8/12",
        "E1": "8/8",
        "E2": "10/10",
        "E3": "10/10",
        "ZH1": "9/10",
        "ZH2": "10/10",
        "ZH3": "6/8",
        "ZH4": "10/10",
        "MA1": "9/12",
        "MA2": "9/12",
        "MA3": "8/8",
        "MA4": "8/8",
        "SC1": "15/15",
        "SC2": "11/15",
        "EN1": "7/8",
        "EN2": "10/10",
        "EN3": "8/10",
        "FR1": "7/9",
        "FR2": "8/9",
        "SC6": "14/14",
        "ZH9": "12/12",
        "ZH10": "12/12",
        "ZH11": "11/11",
        "ZH12": "12/12",
        "MA9": "11/11",
        "MA10": "11/11",
        "MA11": "10/10",
        "MA12": "10/10",
        "SC5": "14/14",
        "EN8": "10/10",
        "EN9": "10/10",
        "EN11": "5/5",
        "EN10": "12/12",
        "FR6": "10/10",
        "ZH13": "12/12",
        "SC7": "13/13",
        "ZH15": "11/11",
        "MA16": "10/10",
        "FR7": "8/10",
        "FR8": "8/10",
        "SC8": "11/13",
        "EN12": "11/12",
        "EN13": "12/12",
        "EN14": "7/8",
        "EN15": "5/5",
        "ZH14": "9/12",
        "ZH16": "10/12",
        "MA13": "11/11",
        "MA14": "11/11",
        "MA15": "10/10",
        "SC9": "16/16",
        "EN16": "14/14",
        "FR9": "10/10",
        "ZH17": "10/13",
        "ZH19": "13/13",
        "ZH18": "9/13",
        "MA20": "12/12",
        "EN17": "14/14",
        "EN19": "5/5",
        "EN18": "14/14",
        "MA18": "12/13",
        "MA17": "13/13",
        "MA19": "12/12",
        "FR10": "10/10",
        "ZH20": "7/13",
        "SC10": "16/16",
        "ZH23": "13/13",
        "SC11": "16/16",
        "SC12": "16/16",
        "EN20": "14/14",
        "FR11": "10/10",
        "MA21": "13/13",
        "MA22": "13/13",
        "FR12": "10/10",
        "ZH21": "13/13",
        "ZH22": "14/14",
        "ZH24": "13/13",
        "EN23": "5/5",
        "EN21": "13/14",
        "EN22": "12/14",
        "MA23": "13/13",
        "MA24": "12/12",
        "MA25": "15/15",
        "MA26": "15/15",
        "ZH27": "15/15",
        "ZH25": "15/15",
        "SC13": "16/16",
        "EN24": "16/16",
        "FR13": "15/15",
        "ZH26": "15/15",
        "ZH28": "15/15",
        "MA27": "15/15",
        "MA28": "15/15"
      },
      "ziDaysDone": [
        1,
        2,
        3,
        4,
        5,
        6,
        7,
        8,
        9,
        10,
        11,
        12,
        13,
        14,
        15,
        16,
        17,
        18,
        19,
        20,
        21,
        22,
        23,
        24,
        25,
        26
      ],
      "ziLearned": 160,
      "ziChars": "读写听想说看她它我你他们哥妈弟妹姐爸书学班校老课时天月日年候后外前里下上石山田水土火树鸟虫花林草跳跑去飞走来小多短大长少肉吃喝鱼饭菜怕哭气笑好爱朋友同高兴远近海河江湖雨雪风节龙舟粽划赛香因为所以但虽然即使无论宁仅应该必须已经却竟居般确实越够始终由各直接受完教室象像等觉错题房间门窗床桌椅灯纸笔画字早晚午点分半把给让找放拿",
      "ziWeak": [
        "及:1",
        "积:1",
        "忘:1",
        "致:1",
        "早:1",
        "午:1",
        "分:1",
        "给:1",
        "找:1",
        "放:1",
        "拿:1"
      ],
      "boxRemaining": 0,
      "writingCount": 0,
      "writing": {},
      "mistakes": [
        {
          "u": "Exponents & Order of Ops III",
          "q": "3² + 4² = ?",
          "x": "17",
          "r": "25",
          "tier": 3
        },
        {
          "u": "Exponents & Order of Ops III",
          "q": "2 × 3² = ?",
          "x": "12",
          "r": "18",
          "tier": 3
        },
        {
          "u": "Exponents & Order of Ops III",
          "q": "20 − 2³ = ?",
          "x": "2",
          "r": "12",
          "tier": 3
        },
        {
          "u": "Exponents & Order of Ops III",
          "q": "(2 + 3)² = ?",
          "x": "36",
          "r": "25",
          "tier": 3
        },
        {
          "u": "Exponents & Order of Ops III",
          "q": "4³ = ?",
          "x": "2",
          "r": "64",
          "tier": 3
        },
        {
          "u": "Exponents & Order of Ops III",
          "q": "18 − 12 ÷ 3 + 2² = ?",
          "x": "6",
          "r": "18",
          "tier": 3
        },
        {
          "u": "Exponents & Order of Ops III",
          "q": "Which expression matches: 'the square of the sum of 4 and 1'?",
          "x": "4 + 1²",
          "r": "(4 + 1)²",
          "tier": 3
        },
        {
          "u": "Exponents & Order of Ops III",
          "q": "Which equations are TRUE? (select all)",
          "x": "(1 + 2)² = 9、2³ = 6",
          "r": "3² = 9、10 − 2² = 6、(1 + 2)² = 9",
          "tier": 3
        },
        {
          "u": "Exponents & Order of Ops III",
          "q": "Which expressions equal 16? (select all)",
          "x": "4 × 4、8 + 8、2⁴",
          "r": "4²、2⁴、8 + 8、4 × 4",
          "tier": 3
        },
        {
          "u": "Integers & the Number Line",
          "q": "4 − 9 = ?",
          "x": "6",
          "r": "-5",
          "tier": 3
        },
        {
          "u": "Integers & the Number Line",
          "q": "−2 − 3 = ?",
          "x": "1",
          "r": "-5",
          "tier": 3
        },
        {
          "u": "Integers & the Number Line",
          "q": "0 − 7 = ?",
          "x": "8",
          "r": "-7",
          "tier": 2
        },
        {
          "u": "Integers & the Number Line",
          "q": "The temperature is −8°C. It rises 5°C. What is it now? (number only)",
          "x": "6",
          "r": "-3",
          "tier": 3
        },
        {
          "u": "Integers & the Number Line",
          "q": "A diver is at −12 m and goes DOWN 6 m more. Where is she? (number only)",
          "x": "3",
          "r": "-18",
          "tier": 3
        },
        {
          "u": "Integers & the Number Line",
          "q": "Order from LEAST to GREATEST: 2, −5, 0, −1",
          "x": "−1, −5, 0, 2",
          "r": "−5, −1, 0, 2",
          "tier": 3
        },
        {
          "u": "Integers & the Number Line",
          "q": "The opposite of −3 is —",
          "x": "0",
          "r": "3",
          "tier": 2
        },
        {
          "u": "Integers & the Number Line",
          "q": "Basement floor B2 in an elevator is best written as —",
          "x": "0.2",
          "r": "−2",
          "tier": 1
        },
        {
          "u": "Integers & the Number Line",
          "q": "Which numbers are LESS than 0? (select all)",
          "x": "−1",
          "r": "−1、−15、−0.5",
          "tier": 3
        },
        {
          "u": "Integers & the Number Line",
          "q": "Which comparisons are TRUE? (select all)",
          "x": "−5 < −2、−3 > 1",
          "r": "−5 < −2、0 > −9、−10 < −1",
          "tier": 3
        },
        {
          "u": "Integers & the Number Line",
          "q": "Which situations describe a NEGATIVE number? (select all)",
          "x": "you earn 10 dollars、parking level B3、the temperature falls to 5 degrees below zero",
          "r": "6 m below sea level、the temperature falls to 5 degrees below zero、parking level B3",
          "tier": 3
        },
        {
          "u": "长文阅读·蚂蚁的城市",
          "q": "蚁后在王国里负责——",
          "x": "挖通道",
          "r": "产卵",
          "tier": 1
        },
        {
          "u": "长文阅读·蚂蚁的城市",
          "q": "最忙的是哪种蚂蚁？它们不做下面哪件事？",
          "x": "兵蚁；产卵",
          "r": "工蚁；守在入口",
          "tier": 3
        },
        {
          "u": "长文阅读·蚂蚁的城市",
          "q": "文中说兵蚁「像门口的卫兵」，这是——",
          "x": "下定义",
          "r": "打比方",
          "tier": 2
        },
        {
          "u": "长文阅读·蚂蚁的城市",
          "q": "同伴能准确找到食物，是因为——",
          "x": "听到了声音",
          "r": "顺着前面蚂蚁留下的气味走",
          "tier": 2
        },
        {
          "u": "长文阅读·蚂蚁的城市",
          "q": "用手指在蚂蚁队伍中间划一下，蚂蚁会乱成一团，原因是——",
          "x": "它们害怕手指",
          "r": "气味路被擦掉了，它们失去了方向",
          "tier": 3
        },
        {
          "u": "长文阅读·蚂蚁的城市",
          "q": "「一个大蚁巢常常住着几万只蚂蚁」用的说明方法是——",
          "x": "提问题",
          "r": "列数字",
          "tier": 2
        },
        {
          "u": "长文阅读·蚂蚁的城市",
          "q": "下面哪些说法与文章相符？（多选）",
          "x": "蚂蚁靠气味和触角传递消息",
          "r": "蚁巢通道最深能到两米多、蚂蚁靠气味和触角传递消息、擦掉气味后蚂蚁会迷路",
          "tier": 3
        },
        {
          "u": "长文阅读·蚂蚁的城市",
          "q": "文中哪些地方用了「打比方」？（多选）",
          "x": "通道能挖到两米多深",
          "r": "蚁巢像一栋倒着建的高楼、蚁后是王国的「心脏」、兵蚁像门口的卫兵",
          "tier": 3
        },
        {
          "u": "长文阅读·蚂蚁的城市",
          "q": "如果给文章换个题目，下面哪些合适？（多选）",
          "x": "《高楼是怎样建成的》",
          "r": "《地下的蚂蚁王国》、《分工合作的小蚂蚁》、《神奇的「气味路」和蚂蚁的家》",
          "tier": 3
        },
        {
          "u": "成语精细辨析 IV",
          "q": "「为了造出这艘船模，他常常________，连饭都忘了吃。」填——",
          "x": "井井有条",
          "r": "废寝忘食",
          "tier": 2
        },
        {
          "u": "成语精细辨析 IV",
          "q": "「练字要________，三天打鱼两天晒网是练不好的。」填——",
          "x": "恍然大悟",
          "r": "持之以恒",
          "tier": 3
        },
        {
          "u": "成语精细辨析 IV",
          "q": "「他________地盯着显微镜，生怕错过任何变化。」填最贴切的成语。",
          "x": "日积月累",
          "r": "目不转睛",
          "tier": 3
        },
        {
          "u": "成语精细辨析 IV",
          "q": "「妹妹________地拼模型，谁叫她都听不见。」填——",
          "x": "川流不息",
          "r": "专心致志",
          "tier": 3
        },
        {
          "u": "成语精细辨析 IV",
          "q": "下面哪句成语用错了？",
          "x": "经过日积月累，他认识了很多字。",
          "r": "他持之以恒地打了一个哈欠。",
          "tier": 3
        },
        {
          "u": "成语精细辨析 IV",
          "q": "哪些句子的成语使用正确？（多选）",
          "x": "他废寝忘食地准备比赛。",
          "r": "他废寝忘食地准备比赛。、展览馆里参观的人络绎不绝。、坚持锻炼要持之以恒。",
          "tier": 3
        },
        {
          "u": "成语精细辨析 IV",
          "q": "哪些搭配是正确的？（多选）",
          "x": "异口同声地点头",
          "r": "字写得一丝不苟、知识靠日积月累、做事持之以恒",
          "tier": 3
        },
        {
          "u": "成语精细辨析 IV",
          "q": "「都等不及了」——「迫不________待」。点选正确的字。",
          "x": "急",
          "r": "及",
          "tier": 3
        },
        {
          "u": "成语精细辨析 IV",
          "q": "「知识要一点一点________累。」点选正确的字。",
          "x": "织",
          "r": "积",
          "tier": 2
        },
        {
          "u": "成语精细辨析 IV",
          "q": "「他读书读得废寝________食。」点选正确的字。",
          "x": "盲",
          "r": "忘",
          "tier": 2
        },
        {
          "u": "成语精细辨析 IV",
          "q": "「专心________志，才能把事做好。」点选正确的字。",
          "x": "至",
          "r": "致",
          "tier": 3
        },
        {
          "u": "Ecosystems & Food Chains",
          "q": "Which chain is in the CORRECT order?",
          "x": "bird → hawk → grass → grasshopper",
          "r": "grass → grasshopper → bird → hawk",
          "tier": 3
        },
        {
          "u": "Ecosystems & Food Chains",
          "q": "Which of these are PRODUCERS? (select all)",
          "x": "grass",
          "r": "seaweed、grass、an oak tree",
          "tier": 3
        },
        {
          "u": "Ecosystems & Food Chains",
          "q": "If the small fish in a lake all died, which effects are LIKELY? (select all)",
          "x": "birds that eat small fish would leave or go hungry",
          "r": "big fish would have less to eat、birds that eat small fish would leave or go hungry、the tiny water plants they ate might grow more",
          "tier": 3
        },
        {
          "u": "Ecosystems & Food Chains",
          "q": "Which statements about ecosystems are TRUE? (select all)",
          "x": "Arrows in a chain point at the food.",
          "r": "Energy enters most ecosystems as sunlight.、Decomposers return nutrients to the soil.、A food web is many chains connected.",
          "tier": 3
        },
        {
          "u": "Reading Poetry: The Harbour at Night",
          "q": "How many STANZAS does this poem have?",
          "x": "two",
          "r": "three",
          "tier": 1
        },
        {
          "u": "Reading Poetry: The Harbour at Night",
          "q": "How many LINES are in each stanza?",
          "x": "twelve",
          "r": "four",
          "tier": 1
        },
        {
          "u": "Reading Poetry: The Harbour at Night",
          "q": "Which word rhymes with 'rest' in stanza 1?",
          "x": "boats",
          "r": "nest",
          "tier": 1
        },
        {
          "u": "Reading Poetry: The Harbour at Night",
          "q": "The rhyme pattern of each stanza is —",
          "x": "ABAB (alternating)",
          "r": "AABB (pairs)",
          "tier": 3
        },
        {
          "u": "Reading Poetry: The Harbour at Night",
          "q": "'Like tired birds that seek their nest' is a —",
          "x": "personification",
          "r": "simile",
          "tier": 2
        },
        {
          "u": "Reading Poetry: The Harbour at Night",
          "q": "The MOOD of this poem is —",
          "x": "scary and stormy",
          "r": "calm and peaceful",
          "tier": 3
        },
        {
          "u": "Reading Poetry: The Harbour at Night",
          "q": "'Morning light unties the ribbons of the night' most likely means —",
          "x": "someone forgot their ribbons",
          "r": "dawn slowly ends the darkness",
          "tier": 3
        },
        {
          "u": "Reading Poetry: The Harbour at Night",
          "q": "Which lines contain SIMILES? (select all)",
          "x": "The lighthouse is a patient eye、Like soft knocks on a wooden door",
          "r": "Like tired birds that seek their nest、Like soft knocks on a wooden door",
          "tier": 3
        },
        {
          "u": "Reading Poetry: The Harbour at Night",
          "q": "Which poetic tools appear in this poem? (select all)",
          "x": "metaphor、simile、personification",
          "r": "simile、metaphor、personification、rhyme",
          "tier": 3
        },
        {
          "u": "Reading Poetry: The Harbour at Night",
          "q": "Which statements about the poem are TRUE? (select all)",
          "x": "The poem ends at sunrise — morning light appears.、The lighthouse beam moves left and right.、The poem describes a violent storm.、The boats are compared to tired birds.",
          "r": "The poem is set at night.、The boats are compared to tired birds.、The lighthouse beam moves left and right.、The poem ends at sunrise — morning light appears.",
          "tier": 3
        },
        {
          "u": "Reading Poetry: The Harbour at Night",
          "q": "Which pairs of words RHYME in this poem? (select all)",
          "x": "light / night",
          "r": "tune / moon、shore / door、light / night、eye / by",
          "tier": 3
        },
        {
          "u": "Verbes en -er · La négation",
          "q": "Complete: 'Je ____ français.' (to speak)",
          "x": "parles",
          "r": "parle",
          "tier": 2
        },
        {
          "u": "Verbes en -er · La négation",
          "q": "Complete: 'Elle ____ à Toronto.' (to live)",
          "x": "habitons",
          "r": "habite",
          "tier": 2
        },
        {
          "u": "Verbes en -er · La négation",
          "q": "'Je ne parle pas anglais.' means —",
          "x": "You do not speak English.",
          "r": "I do not speak English.",
          "tier": 2
        },
        {
          "u": "Verbes en -er · La négation",
          "q": "Which is the correct NEGATIVE of 'Il joue.'?",
          "x": "Ne il joue pas.",
          "r": "Il ne joue pas.",
          "tier": 3
        },
        {
          "u": "Verbes en -er · La négation",
          "q": "Which is correct before a vowel?",
          "x": "Je ne aime pas les épinards.",
          "r": "Je n'aime pas les épinards.",
          "tier": 3
        },
        {
          "u": "Verbes en -er · La négation",
          "q": "'Nous ne mangeons pas de poisson.' means —",
          "x": "They do not eat fish.",
          "r": "We do not eat fish.",
          "tier": 3
        },
        {
          "u": "Verbes en -er · La négation",
          "q": "How do you say 'She does not play'?",
          "x": "Nous ne jouons pas.",
          "r": "Elle ne joue pas.",
          "tier": 3
        },
        {
          "u": "Verbes en -er · La négation",
          "q": "Complete: 'Est-ce que nous ____ ensemble ?' (to play)",
          "x": "joue",
          "r": "jouons",
          "tier": 3
        },
        {
          "u": "Verbes en -er · La négation",
          "q": "Which sentences are CORRECT? (select all)",
          "x": "Elle habitons à Paris.、Je parles très vite.、Nous aimons la mer.",
          "r": "Je parle français.、Tu joues au parc.、Nous aimons la mer.",
          "tier": 3
        },
        {
          "u": "Verbes en -er · La négation",
          "q": "Which are CORRECT negative sentences? (select all)",
          "x": "Il n'aime pas le café.",
          "r": "Je ne joue pas.、Il n'aime pas le café.、Nous ne parlons pas fort.",
          "tier": 3
        },
        {
          "u": "递进与转折专项 + 识字 Day 25",
          "q": "「这条船________跑得快，________特别省油。」填——",
          "x": "尽管…还是…",
          "r": "不但…而且…",
          "tier": 2
        },
        {
          "u": "递进与转折专项 + 识字 Day 25",
          "q": "「________下着大雨，运动会________照常举行。」填——",
          "x": "不是…就是…",
          "r": "尽管…还是…",
          "tier": 2
        },
        {
          "u": "递进与转折专项 + 识字 Day 25",
          "q": "「妹妹________会背这首诗，________能讲出诗的意思。」填——",
          "x": "虽然…但是…",
          "r": "不仅…还…",
          "tier": 3
        },
        {
          "u": "递进与转折专项 + 识字 Day 25",
          "q": "「他________个子不高，________跳得比谁都远。」填——",
          "x": "一…就…",
          "r": "虽然…但是…",
          "tier": 2
        },
        {
          "u": "递进与转折专项 + 识字 Day 25",
          "q": "「爷爷不但会修船，而且会造船。」这句话的关系是——",
          "x": "转折",
          "r": "递进",
          "tier": 2
        },
        {
          "u": "递进与转折专项 + 识字 Day 25",
          "q": "哪些关联词表示「递进」？（多选）",
          "x": "虽然…但是…、不但…而且…、不仅…还…",
          "r": "不但…而且…、不仅…还…、甚至",
          "tier": 3
        },
        {
          "u": "递进与转折专项 + 识字 Day 25",
          "q": "哪些句子用了「转折」关系？（多选）",
          "x": "虽然他很累，但是他坚持跑完了。、一到周末，我们就去图书馆。、他不但会唱歌，而且会跳舞。",
          "r": "虽然他很累，但是他坚持跑完了。、天气尽管很冷，大家还是来了。、这本书很旧，却很有意思。",
          "tier": 3
        },
        {
          "u": "递进与转折专项 + 识字 Day 25",
          "q": "哪些句子的关联词使用正确？（多选）",
          "x": "虽然下雨了，但是比赛照常进行。、妈妈虽然工作忙，但是每天陪我读书。、尽管他不会游泳，还是他喜欢大海。",
          "r": "他不但学习好，而且乐于助人。、虽然下雨了，但是比赛照常进行。、妈妈虽然工作忙，但是每天陪我读书。",
          "tier": 3
        },
        {
          "u": "递进与转折专项 + 识字 Day 25",
          "q": "「他每天很________就起床读书。」点选一个字。",
          "x": "晨",
          "r": "早",
          "tier": 2
        },
        {
          "u": "递进与转折专项 + 识字 Day 25",
          "q": "「中________十二点，太阳最高。」点选一个字。",
          "x": "许",
          "r": "午",
          "tier": 2
        },
        {
          "u": "递进与转折专项 + 识字 Day 25",
          "q": "「一小时有六十________钟。」点选一个字。",
          "x": "纷",
          "r": "分",
          "tier": 2
        },
        {
          "u": "病句门诊 III + 识字 Day 26",
          "q": "「通过这次比赛，使我明白了团结的力量。」怎样修改最恰当？",
          "x": "把「团结」改成「团洁」",
          "r": "删去「通过」或「使」",
          "tier": 3
        },
        {
          "u": "病句门诊 III + 识字 Day 26",
          "q": "「他睡觉前总觉得口渴。」两个「觉」的读音是——",
          "x": "都读 jiào",
          "r": "jiào、jué",
          "tier": 3
        },
        {
          "u": "病句门诊 III + 识字 Day 26",
          "q": "下面哪句话没有语病？",
          "x": "听了老师的话，受到了很大教育。",
          "r": "我们要发扬优点，改正缺点。",
          "tier": 3
        },
        {
          "u": "病句门诊 III + 识字 Day 26",
          "q": "「他大概用了估计十分钟。」这句话的毛病是——",
          "x": "缺少主语",
          "r": "重复啰嗦",
          "tier": 2
        },
        {
          "u": "病句门诊 III + 识字 Day 26",
          "q": "「哥哥________了我一支新铅笔。」点选一个字。",
          "x": "领",
          "r": "给",
          "tier": 2
        },
        {
          "u": "病句门诊 III + 识字 Day 26",
          "q": "「我到处________不到我的橡皮了。」点选一个字。",
          "x": "托",
          "r": "找",
          "tier": 2
        },
        {
          "u": "病句门诊 III + 识字 Day 26",
          "q": "「用完的东西要________回原来的地方。」点选一个字。",
          "x": "方",
          "r": "放",
          "tier": 2
        },
        {
          "u": "病句门诊 III + 识字 Day 26",
          "q": "「请帮我把桌上的书________过来。」点选一个字。",
          "x": "合",
          "r": "拿",
          "tier": 3
        },
        {
          "u": "病句门诊 III + 识字 Day 26",
          "q": "「作业写完要________好，别弄丢。」点选两个字。",
          "x": "放",
          "r": "放好",
          "tier": 3
        },
        {
          "u": "Ratios, Rates & Working Backwards",
          "q": "$12 for 3 notebooks. How much for ONE notebook? (number only)",
          "x": "1",
          "r": "4",
          "tier": 2
        },
        {
          "u": "Ratios, Rates & Working Backwards",
          "q": "A boat travels 45 km in 3 hours. How many km per hour?",
          "x": "3",
          "r": "15",
          "tier": 2
        },
        {
          "u": "Ratios, Rates & Working Backwards",
          "q": "2/3 of a number is 12. What is the number?",
          "x": "4",
          "r": "18",
          "tier": 3
        },
        {
          "u": "Ratios, Rates & Working Backwards",
          "q": "3/4 of a number is 21. What is the number?",
          "x": "6",
          "r": "28",
          "tier": 3
        },
        {
          "u": "Ratios, Rates & Working Backwards",
          "q": "25% of a number is 8. What is the number?",
          "x": "2",
          "r": "32",
          "tier": 3
        },
        {
          "u": "Ratios, Rates & Working Backwards",
          "q": "15% of 80 = ?",
          "x": "2",
          "r": "12",
          "tier": 3
        },
        {
          "u": "Ratios, Rates & Working Backwards",
          "q": "The ratio of boys to girls is 2:3. There are 8 boys. How many girls?",
          "x": "3",
          "r": "12",
          "tier": 3
        },
        {
          "u": "Ratios, Rates & Working Backwards",
          "q": "5/8 − 1/4 = ? (simplest form)",
          "x": "12",
          "r": "3/8",
          "tier": 3
        },
        {
          "u": "Ratios, Rates & Working Backwards",
          "q": "Simplify the ratio 12:18.",
          "x": "12:18 cannot simplify",
          "r": "2:3",
          "tier": 3
        },
        {
          "u": "Ratios, Rates & Working Backwards",
          "q": "Which ratio is EQUIVALENT to 3:5?",
          "x": "9:12",
          "r": "6:10",
          "tier": 2
        },
        {
          "u": "Ratios, Rates & Working Backwards",
          "q": "Which ratios are equivalent to 2:5? (select all)",
          "x": "5:2、8:20",
          "r": "4:10、6:15、8:20",
          "tier": 3
        },
        {
          "u": "Ratios, Rates & Working Backwards",
          "q": "Which are equal to 3/4? (select all)",
          "x": "0.75、9/12、6/8",
          "r": "75%、0.75、6/8、9/12",
          "tier": 3
        },
        {
          "u": "Ratios, Rates & Working Backwards",
          "q": "A recipe uses flour and sugar in the ratio 4:1. Which statements are TRUE? (select all)",
          "x": "12 cups flour needs 3 cups sugar",
          "r": "8 cups flour needs 2 cups sugar、flour is 4 times the sugar、12 cups flour needs 3 cups sugar",
          "tier": 3
        },
        {
          "u": "Geometry IV & Multi-step Problems",
          "q": "A parallelogram has base 8 and height 5. What is its AREA?",
          "x": "1",
          "r": "40",
          "tier": 2
        },
        {
          "u": "Geometry IV & Multi-step Problems",
          "q": "An L-shaped deck is a 10 by 6 rectangle with a 4 by 2 corner cut out. What is its AREA?",
          "x": "8",
          "r": "52",
          "tier": 3
        },
        {
          "u": "Geometry IV & Multi-step Problems",
          "q": "A triangle has base 12 and height 5. What is its AREA?",
          "x": "8",
          "r": "30",
          "tier": 3
        },
        {
          "u": "Geometry IV & Multi-step Problems",
          "q": "A box has volume 60. Its length is 5 and width is 3. What is its HEIGHT?",
          "x": "2",
          "r": "4",
          "tier": 3
        },
        {
          "u": "Geometry IV & Multi-step Problems",
          "q": "A box is 4 by 4 by 7. What is its VOLUME?",
          "x": "1",
          "r": "112",
          "tier": 3
        },
        {
          "u": "Geometry IV & Multi-step Problems",
          "q": "Solve: 2(x + 3) = 14. x = ?",
          "x": "7",
          "r": "4",
          "tier": 3
        },
        {
          "u": "Geometry IV & Multi-step Problems",
          "q": "Solve: 3(x − 2) = 15. x = ?",
          "x": "/",
          "r": "7",
          "tier": 3
        },
        {
          "u": "Geometry IV & Multi-step Problems",
          "q": "Kai buys 3 T-shirts at $12 each and pays with $50. How much CHANGE does he get?",
          "x": "7",
          "r": "14",
          "tier": 3
        },
        {
          "u": "Geometry IV & Multi-step Problems",
          "q": "To find the area of an L-shape, the BEST first move is —",
          "x": "multiply all the numbers you see",
          "r": "split it into rectangles",
          "tier": 2
        },
        {
          "u": "Geometry IV & Multi-step Problems",
          "q": "Which situation needs VOLUME?",
          "x": "how much rope goes around a field",
          "r": "how much water fills an aquarium",
          "tier": 2
        },
        {
          "u": "Geometry IV & Multi-step Problems",
          "q": "Which units measure AREA? (select all)",
          "x": "m²、cm²、cm³",
          "r": "cm²、m²、km²",
          "tier": 3
        },
        {
          "u": "Geometry IV & Multi-step Problems",
          "q": "Which statements are TRUE? (select all)",
          "x": "An L-shape's area can be found by subtracting the notch、Parallelogram area = base × height、Volume of a box = l × w × h",
          "r": "Triangle area = base × height ÷ 2、Parallelogram area = base × height、Volume of a box = l × w × h、An L-shape's area can be found by subtracting the notch",
          "tier": 3
        },
        {
          "u": "Geometry IV & Multi-step Problems",
          "q": "A captain buys 5 boxes of flags. Each box holds 8 flags. She gives away 12. Which steps find how many are LEFT? (select all)",
          "x": "multiply 5 × 8、start from 40、add 5 + 8",
          "r": "multiply 5 × 8、subtract 12 from the total、start from 40",
          "tier": 3
        },
        {
          "u": "Reading: Icebergs",
          "q": "When a huge chunk of ice breaks off a glacier, scientists call it —",
          "x": "melting",
          "r": "calving",
          "tier": 2
        }
      ]
    }
  },
  "_meta": {
    "updatedAt": "2026-07-22T06:23:53.580Z",
    "updatedBy": "study"
  }
}